poetry_pre_commit_plugin/__init__.py
poetry_pre_commit_plugin/plugin.py
poetry_pre_commit_plugin-0.2.2.dist-info/LICENSE
poetry_pre_commit_plugin-0.2.2.dist-info/METADATA
poetry_pre_commit_plugin-0.2.2.dist-info/WHEEL
poetry_pre_commit_plugin-0.2.2.dist-info/entry_points.txt
poetry_pre_commit_plugin-0.2.2.dist-info/RECORD
