Metadata-Version: 2.3
Name: poetry-pre-commit-plugin
Version: 0.2.2
Summary: Poetry plugin for automatically installing pre-commit hook when it is added to a project
Author: Vytautas Strimaitis
Author-email: vstrimaitis@gmail.com
Requires-Python: >=3.7,<4.0
Classifier: Programming Language :: Python :: 3
Classifier: Programming Language :: Python :: 3.7
Classifier: Programming Language :: Python :: 3.8
Classifier: Programming Language :: Python :: 3.9
Classifier: Programming Language :: Python :: 3.10
Classifier: Programming Language :: Python :: 3.11
Classifier: Programming Language :: Python :: 3.12
Classifier: Programming Language :: Python :: 3.13
Requires-Dist: poetry (>=1.0.0,<3.0.0)
Project-URL: Documentation, https://github.com/vstrimaitis/poetry-pre-commit-plugin
Project-URL: Homepage, https://github.com/vstrimaitis/poetry-pre-commit-plugin
